pynblast-0.7.4.dist-info/METADATA
pynblast-0.7.4.dist-info/WHEEL
pynblast/arena.py
pynblast/pynblast.pyi
pynblast/score_matrix.py
pynblast/smat_builder.py
pynblast/util.py
pynblast/__init__.py
pynblast/pynblast.pyd
pynblast-0.7.4.dist-info/RECORD
