Metadata-Version: 2.1
Name: pynblast
Version: 0.7.4
Classifier: Development Status :: 2 - Pre-Alpha
Classifier: Intended Audience :: Developers
Classifier: License :: OSI Approved :: MIT License
Classifier: Natural Language :: English
Classifier: Programming Language :: Python :: 3.9
Classifier: Programming Language :: Python :: 3.10
Classifier: Programming Language :: Python :: 3.11
Classifier: Programming Language :: Python :: 3.12
Requires-Dist: numpy >=1.22.4
Summary: NBLAST neuron morphology comparison in python (over rust)
Author: Chris L. Barnes <chrislloydbarnes@gmail.com>
Author-email: "Chris L. Barnes" <chrislloydbarnes@gmail.com>
License: MIT
Requires-Python: >=3.9
Project-URL: homepage, https://pypi.org/project/pynblast/
Project-URL: documentation, https://pynblast.readthedocs.io/
Project-URL: repository, https://github.com/clbarnes/nblast-rs/nblast-py
